Metadata-Version: 2.1
Name: plover-better-rtf
Version: 1.0.4
Summary: Plover plugin for better RTF handling
Home-page: https://github.com/sammdot/plover-better-rtf
License: UNKNOWN
Keywords: plover plover_plugin
Platform: UNKNOWN
Classifier: Programming Language :: Python :: 3.6
Classifier: Programming Language :: Python :: 3.7
Classifier: Programming Language :: Python :: 3.8
Classifier: Programming Language :: Python :: 3.9
